archextractor/__init__.py
archextractor/archextractor.py
archextractor/utils.py
archextractor-0.1.3.dist-info/licenses/LICENSE
archextractor-0.1.3.dist-info/METADATA
archextractor-0.1.3.dist-info/WHEEL
archextractor-0.1.3.dist-info/top_level.txt
archextractor-0.1.3.dist-info/RECORD
