Metadata-Version: 2.4
Name: archextractor
Version: 0.1.3
Summary: A module for extracting archive files, which wraps the patoolib library, can recursively process nested compressed package files.
Author-email: ChijiangZhai <chijiangzhai@gmail.com>
Maintainer-email: ChijiangZhai <chijiangzhai@gmail.com>
License:                   GNU LESSER GENERAL PUBLIC LICENSE
Project-URL: Homepage, https://github.com/2513502304/ArchExtractor
Project-URL: Repository, https://github.com/2513502304/ArchExtractor.git
Project-URL: Issues, https://github.com/2513502304/ArchExtractor/issues
Keywords: python,archive,uncompress
Classifier: Development Status :: 3 - Alpha
Classifier: Intended Audience :: Developers
Classifier: License :: OSI Approved :: GNU Lesser General Public License v2 or later (LGPLv2+)
Classifier: Operating System :: OS Independent
Classifier: Programming Language :: Python :: 3
Classifier: Programming Language :: Python :: 3 :: Only
Classifier: Programming Language :: Python :: 3.9
Classifier: Programming Language :: Python :: 3.10
Classifier: Programming Language :: Python :: 3.11
Classifier: Programming Language :: Python :: 3.12
Classifier: Programming Language :: Python :: 3.13
Classifier: Programming Language :: Python :: 3.14
Classifier: Programming Language :: Python :: 3.15
Classifier: Topic :: Utilities
Classifier: Topic :: System
Classifier: Topic :: System :: Archiving
Requires-Python: >=3.12
License-File: LICENSE
Requires-Dist: loguru>=0.7.3
Requires-Dist: patool>=4.0.2
Requires-Dist: rich>=14.2.0
Dynamic: license-file
